README.txt
setup.cfg
setup.py
tm/TMDM.py
tm/XSD.py
tm/XTM_10.py
tm/__init__.py
tm/_proto.py
tm/_urlutils.py
tm/interfaces.py
tm/irilib.py
tm/namespace.py
tm/voc.py
tm.egg-info/PKG-INFO
tm.egg-info/SOURCES.txt
tm.egg-info/dependency_links.txt
tm.egg-info/entry_points.txt
tm.egg-info/not-zip-safe
tm.egg-info/top_level.txt
tm/mio/__init__.py
tm/mio/_exceptions.py
tm/mio/_source.py
tm/mio/deserializer.py
tm/mio/handler.py
tm/mio/syntax.py
tm/mio/xmlutils.py